README.rst
setup.py
django_kvtags.egg-info/PKG-INFO
django_kvtags.egg-info/SOURCES.txt
django_kvtags.egg-info/dependency_links.txt
django_kvtags.egg-info/requires.txt
django_kvtags.egg-info/top_level.txt
kvtags/__init__.py
kvtags/admin.py
kvtags/api.py
kvtags/forms.py
kvtags/managers.py
kvtags/models.py
kvtags/urls.py
kvtags/utils.py
kvtags/views.py
kvtags/management/__init__.py
kvtags/management/commands/__init__.py
kvtags/management/commands/import_tags_csv.py
kvtags/migrations/0001_initial.py
kvtags/migrations/__init__.py
kvtags/south_migrations/0001_initial.py
kvtags/south_migrations/__init__.py
kvtags/templates/import_tags.html