Metadata-Version: 1.0
Name: django-kvtags
Version: 1.5.1
Summary: Extensible key-value tagging for Django
Home-page: UNKNOWN
Author: Yigit Ozen
Author-email: UNKNOWN
License: MIT
Platform: UNKNOWN
